quickbooks/__init__.py
quickbooks/batch.py
quickbooks/cdc.py
quickbooks/client.py
quickbooks/exceptions.py
quickbooks/helpers.py
quickbooks/mixins.py
quickbooks/utils.py
quickbooks/objects/__init__.py
quickbooks/objects/account.py
quickbooks/objects/attachable.py
quickbooks/objects/base.py
quickbooks/objects/batchrequest.py
quickbooks/objects/bill.py
quickbooks/objects/billpayment.py
quickbooks/objects/budget.py
quickbooks/objects/changedatacapture.py
quickbooks/objects/company_info.py
quickbooks/objects/companycurrency.py
quickbooks/objects/creditcardpayment.py
quickbooks/objects/creditcardpayment_entity.py
quickbooks/objects/creditmemo.py
quickbooks/objects/customer.py
quickbooks/objects/department.py
quickbooks/objects/deposit.py
quickbooks/objects/detailline.py
quickbooks/objects/employee.py
quickbooks/objects/estimate.py
quickbooks/objects/invoice.py
quickbooks/objects/item.py
quickbooks/objects/journalentry.py
quickbooks/objects/payment.py
quickbooks/objects/paymentmethod.py
quickbooks/objects/purchase.py
quickbooks/objects/purchaseorder.py
quickbooks/objects/refundreceipt.py
quickbooks/objects/salesreceipt.py
quickbooks/objects/tax.py
quickbooks/objects/taxagency.py
quickbooks/objects/taxcode.py
quickbooks/objects/taxrate.py
quickbooks/objects/taxservice.py
quickbooks/objects/term.py
quickbooks/objects/timeactivity.py
quickbooks/objects/trackingclass.py
quickbooks/objects/transfer.py
quickbooks/objects/vendor.py
quickbooks/objects/vendorcredit.py
tests/__init__.py
tests/integration/__init__.py
tests/integration/test_account.py
tests/integration/test_attachable.py
tests/integration/test_base.py
tests/integration/test_bill.py
tests/integration/test_billpayment.py
tests/integration/test_companycurrency.py
tests/integration/test_creditcardpayment_entity.py
tests/integration/test_creditmemo.py
tests/integration/test_customer.py
tests/integration/test_department.py
tests/integration/test_deposit.py
tests/integration/test_employee.py
quickbooks_pinecone-0.8.7.dist-info/LICENSE
quickbooks_pinecone-0.8.7.dist-info/METADATA
quickbooks_pinecone-0.8.7.dist-info/WHEEL
quickbooks_pinecone-0.8.7.dist-info/entry_points.txt
quickbooks_pinecone-0.8.7.dist-info/top_level.txt
quickbooks_pinecone-0.8.7.dist-info/RECORD
