Metadata-Version: 2.1
Name: quickbooks-pinecone
Version: 0.8.7
Summary: A Python library for accessing the QuickBooks API.
Home-page: https://gitlab.com/pinecone-osp/pinecone-quickbooks
Author: Kody Van Ry
Author-email: kody@pineconemobile.com
License: MIT
Keywords: quickbooks,qbo,accounting
Platform: UNKNOWN
Classifier: Development Status :: 3 - Alpha
Classifier: Intended Audience :: Developers
Classifier: License :: OSI Approved :: MIT License
Classifier: Operating System :: OS Independent
Classifier: Programming Language :: Python
Classifier: Programming Language :: Python :: 3.5
Classifier: Programming Language :: Python :: 3.6
Classifier: Programming Language :: Python :: 3.7
Classifier: Programming Language :: Python :: 3.8
Requires-Dist: setuptools
Requires-Dist: intuit-oauth (==1.2.3)
Requires-Dist: rauth (>=0.7.1)
Requires-Dist: authclient
Requires-Dist: requests (>=2.19.1)
Requires-Dist: simplejson (>=3.17.0)
Requires-Dist: six (>=1.14.0)
Requires-Dist: python-dateutil
Requires-Dist: pycparser (==2.18)
